{
  "Joe Biden": ["Joe Biden", "Joseph Biden", "Biden", "President Biden", "Uncle Joe", "Sleepy Joe"],
  "Donald Trump": ["Donald Trump", "Trump", "President Trump", "The Donald", "DJT", "45", "Former President Trump"],
  "Kamala Harris": ["Kamala Harris", "Harris", "Vice President Harris", "Kamala", "VP Harris", "KDH"],
  "Ron DeSantis": ["Ron DeSantis", "DeSantis", "Governor DeSantis", "Ron", "Ron DeSanctimonious"],
  "Gavin Newsom": ["Gavin Newsom", "Newsom", "Governor Newsom", "Gavin", "Governor Hair Gel"],
  "Nikki Haley": ["Nikki Haley", "Haley", "Ambassador Haley", "Nikki", "Nimrata"],
  "Mike Pence": ["Mike Pence", "Pence", "Vice President Pence", "Mike", "Mr. Pious"],
  "Bernie Sanders": ["Bernie Sanders", "Sanders", "Senator Sanders", "Bernie", "Bern", "The Bern"],
  "Chuck Schumer": ["Chuck Schumer", "Schumer", "Senator Schumer", "Majority Leader Schumer", "Cryin' Chuck"],
  "Mitch McConnell": ["Mitch McConnell", "McConnell", "Senator McConnell", "Cocaine Mitch", "Moscow Mitch"],
  "Kevin McCarthy": ["Kevin McCarthy", "McCarthy", "Speaker McCarthy", "Kevin", "My Kevin"],
  "Marjorie Taylor Greene": ["Marjorie Taylor Greene", "MTG", "Greene", "Representative Greene", "Marjorie"],
  "Lauren Boebert": ["Lauren Boebert", "Boebert", "Representative Boebert", "Lauren"],
  "Alexandria Ocasio-Cortez": ["Alexandria Ocasio-Cortez", "AOC", "Ocasio-Cortez", "Alexandria", "Sandy"],
  "Kyrsten Sinema": ["Kyrsten Sinema", "Sinema", "Senator Sinema", "Kyrsten"],
  "Joe Manchin": ["Joe Manchin", "Manchin", "Senator Manchin", "Joe"],
  "Elise Stefanik": ["Elise Stefanik", "Stefanik", "Representative Stefanik", "Elise"],
  "Rashida Tlaib": ["Rashida Tlaib", "Tlaib", "Representative Tlaib", "Rashida"],
  "Ilhan Omar": ["Ilhan Omar", "Omar", "Representative Omar", "Ilhan"],
  "Tim Scott": ["Tim Scott", "Scott", "Senator Scott", "Tim"],
  "Pete Buttigieg": ["Pete Buttigieg", "Buttigieg", "Secretary Buttigieg", "Mayor Pete", "Alfred E. Neuman"],
  "Gretchen Whitmer": ["Gretchen Whitmer", "Whitmer", "Governor Whitmer", "Gretchen", "Big Gretch"],
  "Nancy Pelosi": ["Nancy Pelosi", "Pelosi", "Speaker Pelosi", "Nancy"],
  "Lindsey Graham": ["Lindsey Graham", "Graham", "Senator Graham", "Lindsey"],
  "Elizabeth Warren": ["Elizabeth Warren", "Warren", "Senator Warren", "Liz", "Pocahontas"],
  "Ted Cruz": ["Ted Cruz", "Cruz", "Senator Cruz", "Ted", "Lyin' Ted"],
  "Amy Klobuchar": ["Amy Klobuchar", "Klobuchar", "Senator Klobuchar", "Amy"],
  "Cory Booker": ["Cory Booker", "Booker", "Senator Booker", "Cory"],
  "Josh Hawley": ["Josh Hawley", "Hawley", "Senator Hawley", "Josh"],
  "Tom Cotton": ["Tom Cotton", "Cotton", "Senator Cotton", "Tom"],
  "Kristi Noem": ["Kristi Noem", "Noem", "Governor Noem", "Kristi"],
  "Andrew Cuomo": ["Andrew Cuomo", "Cuomo", "Governor Cuomo", "Andrew"],
  "Bill de Blasio": ["Bill de Blasio", "de Blasio", "Mayor de Blasio", "Bill"],
  "Rudy Giuliani": ["Rudy Giuliani", "Giuliani", "Mayor Giuliani", "Rudy", "America's Mayor"],
  "John Roberts": ["John Roberts", "Roberts", "Chief Justice Roberts", "John"],
  "Clarence Thomas": ["Clarence Thomas", "Thomas", "Justice Thomas", "Clarence"],
  "Sonia Sotomayor": ["Sonia Sotomayor", "Sotomayor", "Justice Sotomayor", "Sonia"],
  "Elena Kagan": ["Elena Kagan", "Kagan", "Justice Kagan", "Elena"],
  "Neil Gorsuch": ["Neil Gorsuch", "Gorsuch", "Justice Gorsuch", "Neil"],
  "Brett Kavanaugh": ["Brett Kavanaugh", "Kavanaugh", "Justice Kavanaugh", "Brett"],
  "Amy Coney Barrett": ["Amy Coney Barrett", "Barrett", "Justice Barrett", "Amy"],
  "Merrick Garland": ["Merrick Garland", "Garland", "Attorney General Garland", "Merrick"],
  "Janet Yellen": ["Janet Yellen", "Yellen", "Secretary Yellen", "Janet"],
  "Antony Blinken": ["Antony Blinken", "Blinken", "Secretary Blinken", "Tony"],
  "Lloyd Austin": ["Lloyd Austin", "Austin", "Secretary Austin", "Lloyd"],
  "Alejandro Mayorkas": ["Alejandro Mayorkas", "Mayorkas", "Secretary Mayorkas", "Ali"],
  "Xavier Becerra": ["Xavier Becerra", "Becerra", "Secretary Becerra", "Xavier"],
  "Deb Haaland": ["Deb Haaland", "Haaland", "Secretary Haaland", "Deb"],
  "Marcia Fudge": ["Marcia Fudge", "Fudge", "Secretary Fudge", "Marcia"],
  "Jennifer Granholm": ["Jennifer Granholm", "Granholm", "Secretary Granholm", "Jennifer"],
  "Miguel Cardona": ["Miguel Cardona", "Cardona", "Secretary Cardona", "Miguel"],
  "Marty Walsh": ["Marty Walsh", "Walsh", "Secretary Walsh", "Marty"],
  "Gina Raimondo": ["Gina Raimondo", "Raimondo", "Secretary Raimondo"]
}